odoo/addons/pos_price_to_weight/README.rst
odoo/addons/pos_price_to_weight/__init__.py
odoo/addons/pos_price_to_weight/__manifest__.py
odoo/addons/pos_price_to_weight/data/barcode_rule.xml
odoo/addons/pos_price_to_weight/demo/product_product.xml
odoo/addons/pos_price_to_weight/i18n/ca.po
odoo/addons/pos_price_to_weight/i18n/es.po
odoo/addons/pos_price_to_weight/i18n/fr.po
odoo/addons/pos_price_to_weight/i18n/it.po
odoo/addons/pos_price_to_weight/i18n/pos_price_to_weight.pot
odoo/addons/pos_price_to_weight/models/__init__.py
odoo/addons/pos_price_to_weight/models/barcode_rule.py
odoo/addons/pos_price_to_weight/models/pos_config.py
odoo/addons/pos_price_to_weight/readme/CONFIGURE.rst
odoo/addons/pos_price_to_weight/readme/CONTRIBUTORS.rst
odoo/addons/pos_price_to_weight/readme/CREDITS.rst
odoo/addons/pos_price_to_weight/readme/DESCRIPTION.rst
odoo/addons/pos_price_to_weight/static/description/barcode_rule.png
odoo/addons/pos_price_to_weight/static/description/icon.png
odoo/addons/pos_price_to_weight/static/description/index.html
odoo/addons/pos_price_to_weight/static/description/pos_config_form.png
odoo/addons/pos_price_to_weight/static/description/pos_test_1.png
odoo/addons/pos_price_to_weight/static/description/pos_test_2.png
odoo/addons/pos_price_to_weight/static/src/js/models.js
odoo/addons/pos_price_to_weight/static/src/js/screens.js
odoo/addons/pos_price_to_weight/views/assets.xml
odoo/addons/pos_price_to_weight/views/view_pos_config.xml
odoo12_addon_pos_price_to_weight-12.0.2.0.1.dist-info/METADATA
odoo12_addon_pos_price_to_weight-12.0.2.0.1.dist-info/WHEEL
odoo12_addon_pos_price_to_weight-12.0.2.0.1.dist-info/top_level.txt
odoo12_addon_pos_price_to_weight-12.0.2.0.1.dist-info/RECORD
